formfieldstash/__init__.py
formfieldstash/admin.py
formfieldstash/helpers.py
formfieldstash/static/formfield_stash/formfield_stash.js
formfieldstash/static/formfield_stash/zzz_adjust-divers.css
formfieldstash/tests/__init__.py
formfieldstash/tests/settings.py
formfieldstash/tests/settings_no_headless.py
formfieldstash/tests/test_admin.py
formfieldstash/tests/urls.py
formfieldstash/tests/test_app/__init__.py
formfieldstash/tests/test_app/admin.py
formfieldstash/tests/test_app/models.py
formfieldstash/tests/test_app/migrations/0001_initial.py
formfieldstash/tests/test_app/migrations/0002_auto_20160714_0808.py
formfieldstash/tests/test_app/migrations/0003_auto_20191114_1039.py
formfieldstash/tests/test_app/migrations/0004_testmodelsingle2.py
formfieldstash/tests/test_app/migrations/0005_auto_20191119_0327.py
formfieldstash/tests/test_app/migrations/0006_auto_20191205_0657.py
formfieldstash/tests/test_app/migrations/0007_auto_20191205_0658.py
formfieldstash/tests/test_app/migrations/__init__.py
formfieldstash/tests/utils/__init__.py
formfieldstash/tests/utils/django_utils.py
formfieldstash/tests/utils/selenium_utils.py
django_formfieldstash-0.1.0.dist-info/LICENSES
django_formfieldstash-0.1.0.dist-info/METADATA
django_formfieldstash-0.1.0.dist-info/WHEEL
django_formfieldstash-0.1.0.dist-info/top_level.txt
django_formfieldstash-0.1.0.dist-info/RECORD
