Metadata-Version: 2.1
Name: django-formfieldstash
Version: 0.1.0
Summary: formfieldstash
Home-page: http://github.com/bnzk/django-formfieldstash
Author: Ben Stähli
Author-email: bnzk@bnzk.ch
License: MIT
Platform: OS Independent
Classifier: Development Status :: 4 - Beta
Classifier: Framework :: Django
Classifier: Intended Audience :: Developers
Classifier: License :: OSI Approved :: MIT License
Classifier: Operating System :: OS Independent
Classifier: Programming Language :: Python
Classifier: Topic :: Internet :: WWW/HTTP
License-File: LICENSES
Requires-Dist: Django (>=1.8)
